Metadata-Version: 1.1
Name: wquantiles
Version: 0.5
Summary: Weighted quantiles, including weighted median, based on numpy
Home-page: http://github.com/nudomarinero/wquantiles/
Author: Jose Sabater
Author-email: jsm@iaa.es
License: MIT License
Platform: any
Classifier: Programming Language :: Python
Classifier: Development Status :: 4 - Beta
Classifier: Natural Language :: English
Classifier: Environment :: Web Environment
Classifier: Intended Audience :: Science/Research
Classifier: License :: OSI Approved :: MIT License
Classifier: Operating System :: OS Independent
Classifier: Topic :: Scientific/Engineering :: Mathematics
Classifier: Topic :: Software Development :: Libraries :: Python Modules
